kuti/__init__.py
kuti/applications.py
kuti/generators.py
kuti/generic.py
kuti/image_augmenter.py
kuti/image_utils.py
kuti/model_helper.py
kuti/tensor_ops.py
kuti-0.9.8.1.dist-info/LICENSE
kuti-0.9.8.1.dist-info/WHEEL
kuti-0.9.8.1.dist-info/METADATA
kuti-0.9.8.1.dist-info/RECORD
