Metadata-Version: 2.1
Name: kuti
Version: 0.9.8.1
Summary: Keras training management utilities.
Home-page: https://github.com/subpic/ku/tree/master
License: MIT
Keywords: Keras,Tensorflow,Training management,Deep learning
Author: Vlad Hosu
Author-email: vladehosu@gmail.com
Maintainer: Vlad Hosu
Maintainer-email: vladehosu@gmail.com
Requires-Python: >=3.6.1
Classifier: License :: OSI Approved :: MIT License
Classifier: Programming Language :: Python :: 3
Classifier: Programming Language :: Python :: 3.10
Classifier: Programming Language :: Python :: 3.7
Classifier: Programming Language :: Python :: 3.8
Classifier: Programming Language :: Python :: 3.9
Requires-Dist: Pillow (>=7,<8)
Requires-Dist: future
Requires-Dist: h5py (>=2.10.0,<3.0.0)
Requires-Dist: matplotlib
Requires-Dist: munch
Requires-Dist: numpy
Requires-Dist: opencv-python
Requires-Dist: pandas
Requires-Dist: scikit-image (>=0.16.2,<0.17.0)
Requires-Dist: scikit-learn (>=0.22.1,<0.23.0)
Requires-Dist: scipy
Project-URL: Repository, https://github.com/subpic/ku/tree/master
